{
	"IDR00004": {
		"name": "IDR00004",
		"range": 999,
		"bounds": [
			[
				113,
				-6
			],
			[
				154,
				-5
			],
			[
				158,
				-46
			],
			[
				110,
				-44
			]
		],
		"title": "National",
		"images": [
			{
				"fileName": "IDR00004.T.202102220448.png",
				"origSource": "http://www.bom.gov.au/radar/IDR00004.T.202102220448.png",
				"source": "https://lh3.googleusercontent.com/d/1xcNYI40BwHymyeqfTz0JlGjVn68hoG7S",
				"imageDate": "2021-02-22T04:48:00.000Z"
			},
			{
				"fileName": "IDR00004.T.202102220548.png",
				"origSource": "http://www.bom.gov.au/radar/IDR00004.T.202102220548.png",
				"source": "https://lh3.googleusercontent.com/d/1ESaY82eWLjEATvkkDWBt0ADa0PwyI-eY",
				"imageDate": "2021-02-22T05:48:00.000Z"
			},
			{
				"fileName": "IDR00004.T.202102220648.png",
				"origSource": "http://www.bom.gov.au/radar/IDR00004.T.202102220648.png",
				"source": "https://lh3.googleusercontent.com/d/1IEf7pms_Yzc2bl4SzgokmL439tH0KpmW",
				"imageDate": "2021-02-22T06:48:00.000Z"
			},
			{
				"fileName": "IDR00004.T.202102220748.png",
				"origSource": "http://www.bom.gov.au/radar/IDR00004.T.202102220748.png",
				"source": "https://lh3.googleusercontent.com/d/1yjCPHyZGBAWRiQhF-BnweS7KIrT8Uluh",
				"imageDate": "2021-02-22T07:48:00.000Z"
			}
		],
		"error": null
	},
	"IDR081": {
		"name": "IDR081",
		"range": 512,
		"bounds": [
			[
				147.67746,
				-21.27933
			],
			[
				157.5181,
				-21.27847
			],
			[
				157.91824,
				-30.43973
			],
			[
				147.27968,
				-30.44103
			]
		],
		"title": "512 km composite Gympie (Mt Kanigan)",
		"images": [
			{
				"fileName": "IDR081.T.202102220751.png",
				"origSource": "http://www.bom.gov.au/radar/IDR081.T.202102220751.png",
				"source": "https://lh3.googleusercontent.com/d/1VKPMUD_Zddd1vCTwOGrDjdqOzJqNFKFY",
				"imageDate": "2021-02-22T07:51:00.000Z"
			},
			{
				"fileName": "IDR081.T.202102220756.png",
				"origSource": "http://www.bom.gov.au/radar/IDR081.T.202102220756.png",
				"source": "https://lh3.googleusercontent.com/d/1MkUTU4mM1YuYDgSEdg59mu4CDW8kaWfA",
				"imageDate": "2021-02-22T07:56:00.000Z"
			},
			{
				"fileName": "IDR081.T.202102220801.png",
				"origSource": "http://www.bom.gov.au/radar/IDR081.T.202102220801.png",
				"source": "https://lh3.googleusercontent.com/d/1N6nQwJbgUkLs6sPnsuQiYAtshQZNx8rb",
				"imageDate": "2021-02-22T08:01:00.000Z"
			},
			{
				"fileName": "IDR081.T.202102220806.png",
				"origSource": "http://www.bom.gov.au/radar/IDR081.T.202102220806.png",
				"source": "https://lh3.googleusercontent.com/d/1GsNBTidUzV8DtZgG59XN9wtOd0Q_Asvf",
				"imageDate": "2021-02-22T08:06:00.000Z"
			},
			{
				"fileName": "IDR081.T.202102220811.png",
				"origSource": "http://www.bom.gov.au/radar/IDR081.T.202102220811.png",
				"source": "https://lh3.googleusercontent.com/d/1vQtQJZlULRqjbHf8BNtr5BylQDfF4wOA",
				"imageDate": "2021-02-22T08:11:00.000Z"
			},
			{
				"fileName": "IDR081.T.202102220816.png",
				"origSource": "http://www.bom.gov.au/radar/IDR081.T.202102220816.png",
				"source": "https://lh3.googleusercontent.com/d/1I_nP_JWp6l0r33eQb6sHReEZuNSkOMtR",
				"imageDate": "2021-02-22T08:16:00.000Z"
			},
			{
				"fileName": "IDR081.T.202102220821.png",
				"origSource": "http://www.bom.gov.au/radar/IDR081.T.202102220821.png",
				"source": "https://lh3.googleusercontent.com/d/1rWIV41W0w7x17zSldNFsd-hANHsCOUwd",
				"imageDate": "2021-02-22T08:21:00.000Z"
			}
		],
		"error": null
	},
	"IDR082": {
		"name": "IDR082",
		"range": 256,
		"bounds": [
			[
				150.08131,
				-23.6347
			],
			[
				155.10512,
				-23.63437
			],
			[
				155.20573,
				-28.23566
			],
			[
				149.98151,
				-28.23606
			]
		],
		"title": "256 km Gympie (Mt Kanigan)",
		"images": [
			{
				"fileName": "IDR082.T.202102220749.png",
				"origSource": "http://www.bom.gov.au/radar/IDR082.T.202102220749.png",
				"source": "https://lh3.googleusercontent.com/d/1v7fE5dJ2XN3UMD_hZA3l5OVhjKnghHVm",
				"imageDate": "2021-02-22T07:49:00.000Z"
			},
			{
				"fileName": "IDR082.T.202102220754.png",
				"origSource": "http://www.bom.gov.au/radar/IDR082.T.202102220754.png",
				"source": "https://lh3.googleusercontent.com/d/1xibXjeaKfjAuxF26vkIsH7aCOs1OT9KD",
				"imageDate": "2021-02-22T07:54:00.000Z"
			},
			{
				"fileName": "IDR082.T.202102220759.png",
				"origSource": "http://www.bom.gov.au/radar/IDR082.T.202102220759.png",
				"source": "https://lh3.googleusercontent.com/d/1Br1iG-ET3cv02rrZJ93tbhjk0walnA4T",
				"imageDate": "2021-02-22T07:59:00.000Z"
			},
			{
				"fileName": "IDR082.T.202102220804.png",
				"origSource": "http://www.bom.gov.au/radar/IDR082.T.202102220804.png",
				"source": "https://lh3.googleusercontent.com/d/1uhxcOzleysgzDKLFYfpfFenYpU8kpaL-",
				"imageDate": "2021-02-22T08:04:00.000Z"
			},
			{
				"fileName": "IDR082.T.202102220809.png",
				"origSource": "http://www.bom.gov.au/radar/IDR082.T.202102220809.png",
				"source": "https://lh3.googleusercontent.com/d/1rdz9BpH7lqywd41YBLiJP3x5mu0p5c3k",
				"imageDate": "2021-02-22T08:09:00.000Z"
			},
			{
				"fileName": "IDR082.T.202102220814.png",
				"origSource": "http://www.bom.gov.au/radar/IDR082.T.202102220814.png",
				"source": "https://lh3.googleusercontent.com/d/1MUw7NK3RAY3DhDE845YkfuwArH2FkA_G",
				"imageDate": "2021-02-22T08:14:00.000Z"
			},
			{
				"fileName": "IDR082.T.202102220819.png",
				"origSource": "http://www.bom.gov.au/radar/IDR082.T.202102220819.png",
				"source": "https://lh3.googleusercontent.com/d/1p9JiYRKV4S8DKsRN8h66K0Y6cnzlXToq",
				"imageDate": "2021-02-22T08:19:00.000Z"
			}
		],
		"error": null
	},
	"IDR083": {
		"name": "IDR083",
		"range": 128,
		"bounds": [
			[
				151.32056,
				-24.8072
			],
			[
				153.85368,
				-24.80713
			],
			[
				153.87877,
				-27.10637
			],
			[
				151.29564,
				-27.10645
			]
		],
		"title": "128 km Gympie (Mt Kanigan)",
		"images": [
			{
				"fileName": "IDR083.T.202102220749.png",
				"origSource": "http://www.bom.gov.au/radar/IDR083.T.202102220749.png",
				"source": "https://lh3.googleusercontent.com/d/13eoXGdXCRzWPJW3-L-OmxAbfVT4jkwNO",
				"imageDate": "2021-02-22T07:49:00.000Z"
			},
			{
				"fileName": "IDR083.T.202102220754.png",
				"origSource": "http://www.bom.gov.au/radar/IDR083.T.202102220754.png",
				"source": "https://lh3.googleusercontent.com/d/1jenKiOe-Z4xQJT-Vmr5yT2BubGNbXd_D",
				"imageDate": "2021-02-22T07:54:00.000Z"
			},
			{
				"fileName": "IDR083.T.202102220759.png",
				"origSource": "http://www.bom.gov.au/radar/IDR083.T.202102220759.png",
				"source": "https://lh3.googleusercontent.com/d/1Ax5IEVJd2XROtscfxrPqxuqAYZD3ts3O",
				"imageDate": "2021-02-22T07:59:00.000Z"
			},
			{
				"fileName": "IDR083.T.202102220804.png",
				"origSource": "http://www.bom.gov.au/radar/IDR083.T.202102220804.png",
				"source": "https://lh3.googleusercontent.com/d/1CP1OcQSyEotDZqPYfrtvpwcd-EuRn1Zy",
				"imageDate": "2021-02-22T08:04:00.000Z"
			},
			{
				"fileName": "IDR083.T.202102220809.png",
				"origSource": "http://www.bom.gov.au/radar/IDR083.T.202102220809.png",
				"source": "https://lh3.googleusercontent.com/d/1Ps7oQtH5_TLC0bQwEiyv9bpGOyaa3FLE",
				"imageDate": "2021-02-22T08:09:00.000Z"
			},
			{
				"fileName": "IDR083.T.202102220814.png",
				"origSource": "http://www.bom.gov.au/radar/IDR083.T.202102220814.png",
				"source": "https://lh3.googleusercontent.com/d/1Lw3mmaTOL2HJ9wlAjestfdISpmDA_WBn",
				"imageDate": "2021-02-22T08:14:00.000Z"
			},
			{
				"fileName": "IDR083.T.202102220819.png",
				"origSource": "http://www.bom.gov.au/radar/IDR083.T.202102220819.png",
				"source": "https://lh3.googleusercontent.com/d/1hLAaulwwquF7mYgPdE-AXlw4MQUjAc7V",
				"imageDate": "2021-02-22T08:19:00.000Z"
			}
		],
		"error": null
	},
	"IDR084": {
		"name": "IDR084",
		"range": 64,
		"bounds": [
			[
				151.9492,
				-25.38838
			],
			[
				153.22186,
				-25.38836
			],
			[
				153.22813,
				-26.53809
			],
			[
				151.94298,
				-26.53811
			]
		],
		"title": "64 km Gympie (Mt Kanigan)",
		"images": [
			{
				"fileName": "IDR084.T.202102220749.png",
				"origSource": "http://www.bom.gov.au/radar/IDR084.T.202102220749.png",
				"source": "https://lh3.googleusercontent.com/d/11lqCFS4OO5CUQobJNtwf-NyADV39n8DO",
				"imageDate": "2021-02-22T07:49:00.000Z"
			},
			{
				"fileName": "IDR084.T.202102220754.png",
				"origSource": "http://www.bom.gov.au/radar/IDR084.T.202102220754.png",
				"source": "https://lh3.googleusercontent.com/d/1RBpeIVRrj-ooHm4Kp1JQqQ2cXAeetc8Q",
				"imageDate": "2021-02-22T07:54:00.000Z"
			},
			{
				"fileName": "IDR084.T.202102220759.png",
				"origSource": "http://www.bom.gov.au/radar/IDR084.T.202102220759.png",
				"source": "https://lh3.googleusercontent.com/d/1LNHF5o5Ueze3Jd54SzXt5bcidTkXvS35",
				"imageDate": "2021-02-22T07:59:00.000Z"
			},
			{
				"fileName": "IDR084.T.202102220804.png",
				"origSource": "http://www.bom.gov.au/radar/IDR084.T.202102220804.png",
				"source": "https://lh3.googleusercontent.com/d/1ad3SKwyCQqR95wnSeGODH5IgbSQm_-JV",
				"imageDate": "2021-02-22T08:04:00.000Z"
			},
			{
				"fileName": "IDR084.T.202102220809.png",
				"origSource": "http://www.bom.gov.au/radar/IDR084.T.202102220809.png",
				"source": "https://lh3.googleusercontent.com/d/1DzxobRrF9_fHcrjvUVEoOl_F4tLiIzv1",
				"imageDate": "2021-02-22T08:09:00.000Z"
			},
			{
				"fileName": "IDR084.T.202102220814.png",
				"origSource": "http://www.bom.gov.au/radar/IDR084.T.202102220814.png",
				"source": "https://lh3.googleusercontent.com/d/1_kH6sGEYYblPKxp_fLmWw_p7Gvq-H1sF",
				"imageDate": "2021-02-22T08:14:00.000Z"
			},
			{
				"fileName": "IDR084.T.202102220819.png",
				"origSource": "http://www.bom.gov.au/radar/IDR084.T.202102220819.png",
				"source": "https://lh3.googleusercontent.com/d/1pxGSTX34he3B7tS4y7vl-KZYb3SlItFl",
				"imageDate": "2021-02-22T08:19:00.000Z"
			}
		],
		"error": null
	},
	"IDR501": {
		"name": "IDR501",
		"range": 512,
		"bounds": [
			[
				147.58037,
				-22.91182
			],
			[
				157.54222,
				-22.91043
			],
			[
				157.97934,
				-32.07642
			],
			[
				147.14708,
				-32.07849
			]
		],
		"title": "512 km composite Brisbane (Marburg)",
		"images": [
			{
				"fileName": "IDR501.T.202102220737.png",
				"origSource": "http://www.bom.gov.au/radar/IDR501.T.202102220737.png",
				"source": "https://lh3.googleusercontent.com/d/1spic5hYudJVylHQKnZj04rgg6KBeIlDF",
				"imageDate": "2021-02-22T07:37:00.000Z"
			},
			{
				"fileName": "IDR501.T.202102220737.png",
				"origSource": "http://www.bom.gov.au/radar/IDR501.T.202102220737.png",
				"source": "https://lh3.googleusercontent.com/d/1spic5hYudJVylHQKnZj04rgg6KBeIlDF",
				"imageDate": "2021-02-22T07:37:00.000Z"
			},
			{
				"fileName": "IDR501.T.202102220747.png",
				"origSource": "http://www.bom.gov.au/radar/IDR501.T.202102220747.png",
				"source": "https://lh3.googleusercontent.com/d/1JLbsSk1UxCoELEAUto7fFiqlHgHATcR4",
				"imageDate": "2021-02-22T07:47:00.000Z"
			},
			{
				"fileName": "IDR501.T.202102220757.png",
				"origSource": "http://www.bom.gov.au/radar/IDR501.T.202102220757.png",
				"source": "https://lh3.googleusercontent.com/d/1l1Irlsa_IpKDOko79VAXt8kF_JjqyGLI",
				"imageDate": "2021-02-22T07:57:00.000Z"
			},
			{
				"fileName": "IDR501.T.202102220807.png",
				"origSource": "http://www.bom.gov.au/radar/IDR501.T.202102220807.png",
				"source": "https://lh3.googleusercontent.com/d/1vnJ5ZOJ2qTw0fty_zScWw_F6ZSLsDhU6",
				"imageDate": "2021-02-22T08:07:00.000Z"
			},
			{
				"fileName": "IDR501.T.202102220817.png",
				"origSource": "http://www.bom.gov.au/radar/IDR501.T.202102220817.png",
				"source": "https://lh3.googleusercontent.com/d/1AezFPF9fc4uZDzNPn4EFI7neSyRncgSM",
				"imageDate": "2021-02-22T08:17:00.000Z"
			}
		],
		"error": null
	},
	"IDR502": {
		"name": "IDR502",
		"range": 256,
		"bounds": [
			[
				150.00761,
				-25.27519
			],
			[
				155.09239,
				-25.27482
			],
			[
				155.20183,
				-29.87152
			],
			[
				149.89912,
				-29.87198
			]
		],
		"title": "256 km Brisbane (Marburg)",
		"images": [
			{
				"fileName": "IDR502.T.202102220740.png",
				"origSource": "http://www.bom.gov.au/radar/IDR502.T.202102220740.png",
				"source": "https://lh3.googleusercontent.com/d/1Tv58V_eTe5dYFmIkcXJ9aIrf2gCowdVh",
				"imageDate": "2021-02-22T07:40:00.000Z"
			},
			{
				"fileName": "IDR502.T.202102220740.png",
				"origSource": "http://www.bom.gov.au/radar/IDR502.T.202102220740.png",
				"source": "https://lh3.googleusercontent.com/d/1Tv58V_eTe5dYFmIkcXJ9aIrf2gCowdVh",
				"imageDate": "2021-02-22T07:40:00.000Z"
			},
			{
				"fileName": "IDR502.T.202102220750.png",
				"origSource": "http://www.bom.gov.au/radar/IDR502.T.202102220750.png",
				"source": "https://lh3.googleusercontent.com/d/1TKW0ss6u3T6P-crDRY-o_H2zCY6BKSbS",
				"imageDate": "2021-02-22T07:50:00.000Z"
			},
			{
				"fileName": "IDR502.T.202102220800.png",
				"origSource": "http://www.bom.gov.au/radar/IDR502.T.202102220800.png",
				"source": "https://lh3.googleusercontent.com/d/1bOX2hu2xXn4ghFsosD2Z2XdisBRNoEry",
				"imageDate": "2021-02-22T08:00:00.000Z"
			},
			{
				"fileName": "IDR502.T.202102220810.png",
				"origSource": "http://www.bom.gov.au/radar/IDR502.T.202102220810.png",
				"source": "https://lh3.googleusercontent.com/d/1ZLl_0kdN5ArpucGEV3Zz9xYiBJtUcvio",
				"imageDate": "2021-02-22T08:10:00.000Z"
			},
			{
				"fileName": "IDR502.T.202102220820.png",
				"origSource": "http://www.bom.gov.au/radar/IDR502.T.202102220820.png",
				"source": "https://lh3.googleusercontent.com/d/1Ocdgd1TbZ0aN6qcTUSZ_FPryOycgD7Zc",
				"imageDate": "2021-02-22T08:20:00.000Z"
			}
		],
		"error": null
	},
	"IDR503": {
		"name": "IDR503",
		"range": 128,
		"bounds": [
			[
				151.26024,
				-26.44776
			],
			[
				153.8297,
				-26.44766
			],
			[
				153.85709,
				-28.74804
			],
			[
				151.23309,
				-28.74816
			]
		],
		"title": "128 km Brisbane (Marburg)",
		"images": [
			{
				"fileName": "IDR503.T.202102220740.png",
				"origSource": "http://www.bom.gov.au/radar/IDR503.T.202102220740.png",
				"source": "https://lh3.googleusercontent.com/d/12LeBMG6hfYrNC5sd_2eXOjaDktH8jAHQ",
				"imageDate": "2021-02-22T07:40:00.000Z"
			},
			{
				"fileName": "IDR503.T.202102220740.png",
				"origSource": "http://www.bom.gov.au/radar/IDR503.T.202102220740.png",
				"source": "https://lh3.googleusercontent.com/d/12LeBMG6hfYrNC5sd_2eXOjaDktH8jAHQ",
				"imageDate": "2021-02-22T07:40:00.000Z"
			},
			{
				"fileName": "IDR503.T.202102220750.png",
				"origSource": "http://www.bom.gov.au/radar/IDR503.T.202102220750.png",
				"source": "https://lh3.googleusercontent.com/d/1BjSpDu9Um-ryvBHHahQIAIkOX_Ndyu8_",
				"imageDate": "2021-02-22T07:50:00.000Z"
			},
			{
				"fileName": "IDR503.T.202102220800.png",
				"origSource": "http://www.bom.gov.au/radar/IDR503.T.202102220800.png",
				"source": "https://lh3.googleusercontent.com/d/1CmLf98DvKZRmbS6UraMbCnzzO9MwUS8G",
				"imageDate": "2021-02-22T08:00:00.000Z"
			},
			{
				"fileName": "IDR503.T.202102220810.png",
				"origSource": "http://www.bom.gov.au/radar/IDR503.T.202102220810.png",
				"source": "https://lh3.googleusercontent.com/d/1_Bd6SmTlq9elxKJGDIxmMDU0E7QZUAZV",
				"imageDate": "2021-02-22T08:10:00.000Z"
			},
			{
				"fileName": "IDR503.T.202102220820.png",
				"origSource": "http://www.bom.gov.au/radar/IDR503.T.202102220820.png",
				"source": "https://lh3.googleusercontent.com/d/1pGulNBUcvjDRDXV2oso9jNWO-3s_OTAe",
				"imageDate": "2021-02-22T08:20:00.000Z"
			}
		],
		"error": null
	},
	"IDR531": {
		"name": "IDR531",
		"range": 512,
		"bounds": [
			[
				144.81091,
				-24.79223
			],
			[
				154.92836,
				-24.79091
			],
			[
				155.41046,
				-33.96424
			],
			[
				144.33249,
				-33.96617
			]
		],
		"title": "512 km composite Moree",
		"images": [
			{
				"fileName": "IDR531.T.202102220751.png",
				"origSource": "http://www.bom.gov.au/radar/IDR531.T.202102220751.png",
				"source": "https://lh3.googleusercontent.com/d/19yOkw8xo8GwKbn1MaH-kBEp9PXIZ4IwP",
				"imageDate": "2021-02-22T07:51:00.000Z"
			},
			{
				"fileName": "IDR531.T.202102220756.png",
				"origSource": "http://www.bom.gov.au/radar/IDR531.T.202102220756.png",
				"source": "https://lh3.googleusercontent.com/d/1gC7N4IXDNunaZ8ZJmH_dU7bGwGGPtyay",
				"imageDate": "2021-02-22T07:56:00.000Z"
			},
			{
				"fileName": "IDR531.T.202102220801.png",
				"origSource": "http://www.bom.gov.au/radar/IDR531.T.202102220801.png",
				"source": "https://lh3.googleusercontent.com/d/1LZSPzeBe4g4yiIU1Ul3Xz2CiWLllrOnH",
				"imageDate": "2021-02-22T08:01:00.000Z"
			},
			{
				"fileName": "IDR531.T.202102220806.png",
				"origSource": "http://www.bom.gov.au/radar/IDR531.T.202102220806.png",
				"source": "https://lh3.googleusercontent.com/d/1PIp1jmQqoPvqurxAlDIqEg-TkNHQ6iYS",
				"imageDate": "2021-02-22T08:06:00.000Z"
			},
			{
				"fileName": "IDR531.T.202102220811.png",
				"origSource": "http://www.bom.gov.au/radar/IDR531.T.202102220811.png",
				"source": "https://lh3.googleusercontent.com/d/1XrmnFYJ_KPigoV3tpt4q7xzsJjKxq2bp",
				"imageDate": "2021-02-22T08:11:00.000Z"
			},
			{
				"fileName": "IDR531.T.202102220816.png",
				"origSource": "http://www.bom.gov.au/radar/IDR531.T.202102220816.png",
				"source": "https://lh3.googleusercontent.com/d/1G2JNgT-M5qUISO1j8R2l8ngG2Hw5vWSZ",
				"imageDate": "2021-02-22T08:16:00.000Z"
			},
			{
				"fileName": "IDR531.T.202102220821.png",
				"origSource": "http://www.bom.gov.au/radar/IDR531.T.202102220821.png",
				"source": "https://lh3.googleusercontent.com/d/1PaVM-YlZzZ_7dTn3QTc7w_AwevGYc1ez",
				"imageDate": "2021-02-22T08:21:00.000Z"
			}
		],
		"error": null
	},
	"IDR532": {
		"name": "IDR532",
		"range": 256,
		"bounds": [
			[
				147.27092,
				-27.16231
			],
			[
				152.44925,
				-27.16194
			],
			[
				152.57022,
				-31.76767
			],
			[
				147.15088,
				-31.76811
			]
		],
		"title": "256 km Moree",
		"images": [
			{
				"fileName": "IDR532.T.202102220745.png",
				"origSource": "http://www.bom.gov.au/radar/IDR532.T.202102220745.png",
				"source": "https://lh3.googleusercontent.com/d/1KeLE05zOucmtC15Jsf2Z-9pQuXI5lwvM",
				"imageDate": "2021-02-22T07:45:00.000Z"
			},
			{
				"fileName": "IDR532.T.202102220750.png",
				"origSource": "http://www.bom.gov.au/radar/IDR532.T.202102220750.png",
				"source": "https://lh3.googleusercontent.com/d/1vKuhQ8SZyCxo6b3bshBy3l7cMlYwMWMg",
				"imageDate": "2021-02-22T07:50:00.000Z"
			},
			{
				"fileName": "IDR532.T.202102220755.png",
				"origSource": "http://www.bom.gov.au/radar/IDR532.T.202102220755.png",
				"source": "https://lh3.googleusercontent.com/d/11OTFnl_GNYhsrW4WH4auqCKVJqme_stA",
				"imageDate": "2021-02-22T07:55:00.000Z"
			},
			{
				"fileName": "IDR532.T.202102220800.png",
				"origSource": "http://www.bom.gov.au/radar/IDR532.T.202102220800.png",
				"source": "https://lh3.googleusercontent.com/d/1MI1Cq0fm7ycz7XIPFG3VEC17EmKnbCvS",
				"imageDate": "2021-02-22T08:00:00.000Z"
			},
			{
				"fileName": "IDR532.T.202102220805.png",
				"origSource": "http://www.bom.gov.au/radar/IDR532.T.202102220805.png",
				"source": "https://lh3.googleusercontent.com/d/1RY5JmhTIDEmPOjglqh3Bozr1faXqfxKD",
				"imageDate": "2021-02-22T08:05:00.000Z"
			},
			{
				"fileName": "IDR532.T.202102220810.png",
				"origSource": "http://www.bom.gov.au/radar/IDR532.T.202102220810.png",
				"source": "https://lh3.googleusercontent.com/d/1tGIXXqfiUnuTaRQX_kPps5WnKjZcZSd6",
				"imageDate": "2021-02-22T08:10:00.000Z"
			},
			{
				"fileName": "IDR532.T.202102220815.png",
				"origSource": "http://www.bom.gov.au/radar/IDR532.T.202102220815.png",
				"source": "https://lh3.googleusercontent.com/d/1XPxvHw-KggPir1hTnAPfkBPx8YfavkpJ",
				"imageDate": "2021-02-22T08:15:00.000Z"
			}
		],
		"error": null
	},
	"IDR533": {
		"name": "IDR533",
		"range": 128,
		"bounds": [
			[
				148.54645,
				-28.33886
			],
			[
				151.16147,
				-28.33879
			],
			[
				151.19162,
				-30.64022
			],
			[
				148.51648,
				-30.6403
			]
		],
		"title": "128 km Moree",
		"images": [
			{
				"fileName": "IDR533.T.202102220745.png",
				"origSource": "http://www.bom.gov.au/radar/IDR533.T.202102220745.png",
				"source": "https://lh3.googleusercontent.com/d/1qDzh5jFM4zCSwIVczGoLCB_sWPuxgAWI",
				"imageDate": "2021-02-22T07:45:00.000Z"
			},
			{
				"fileName": "IDR533.T.202102220750.png",
				"origSource": "http://www.bom.gov.au/radar/IDR533.T.202102220750.png",
				"source": "https://lh3.googleusercontent.com/d/1F0j6iIy152Uhcx_wsqwbX0yB3SC6NoDA",
				"imageDate": "2021-02-22T07:50:00.000Z"
			},
			{
				"fileName": "IDR533.T.202102220755.png",
				"origSource": "http://www.bom.gov.au/radar/IDR533.T.202102220755.png",
				"source": "https://lh3.googleusercontent.com/d/1sNM41Hy6hgwgedVc2D7t2Xj7nJKsntOz",
				"imageDate": "2021-02-22T07:55:00.000Z"
			},
			{
				"fileName": "IDR533.T.202102220800.png",
				"origSource": "http://www.bom.gov.au/radar/IDR533.T.202102220800.png",
				"source": "https://lh3.googleusercontent.com/d/1orvPQKvQ6Qp7HznyT4VhpnyOSNEZnzY3",
				"imageDate": "2021-02-22T08:00:00.000Z"
			},
			{
				"fileName": "IDR533.T.202102220805.png",
				"origSource": "http://www.bom.gov.au/radar/IDR533.T.202102220805.png",
				"source": "https://lh3.googleusercontent.com/d/151F6DaIOMtF0DwSjRwZWSdRHF-qdnQsm",
				"imageDate": "2021-02-22T08:05:00.000Z"
			},
			{
				"fileName": "IDR533.T.202102220810.png",
				"origSource": "http://www.bom.gov.au/radar/IDR533.T.202102220810.png",
				"source": "https://lh3.googleusercontent.com/d/12iCNXkLZKLLoGUs18NMrv0esOeuCKnGS",
				"imageDate": "2021-02-22T08:10:00.000Z"
			},
			{
				"fileName": "IDR533.T.202102220815.png",
				"origSource": "http://www.bom.gov.au/radar/IDR533.T.202102220815.png",
				"source": "https://lh3.googleusercontent.com/d/1AxiSSt2xPyPpUIQzo5bShpdodqGelJYL",
				"imageDate": "2021-02-22T08:15:00.000Z"
			}
		],
		"error": null
	},
	"IDR661": {
		"name": "IDR661",
		"range": 512,
		"bounds": [
			[
				148.2706,
				-23.00939
			],
			[
				158.24875,
				-23.00815
			],
			[
				158.68889,
				-32.18254
			],
			[
				147.83388,
				-32.18437
			]
		],
		"title": "512 km composite Brisbane (Mt Stapylton)",
		"images": [
			{
				"fileName": "IDR661.T.202102220747.png",
				"origSource": "http://www.bom.gov.au/radar/IDR661.T.202102220747.png",
				"source": "https://lh3.googleusercontent.com/d/1amA_5xWYN6QcKkzpgOdP-OQiVW5cAn7T",
				"imageDate": "2021-02-22T07:47:00.000Z"
			},
			{
				"fileName": "IDR661.T.202102220747.png",
				"origSource": "http://www.bom.gov.au/radar/IDR661.T.202102220747.png",
				"source": "https://lh3.googleusercontent.com/d/1amA_5xWYN6QcKkzpgOdP-OQiVW5cAn7T",
				"imageDate": "2021-02-22T07:47:00.000Z"
			},
			{
				"fileName": "IDR661.T.202102220753.png",
				"origSource": "http://www.bom.gov.au/radar/IDR661.T.202102220753.png",
				"source": "https://lh3.googleusercontent.com/d/1007oDsLIgp8SX7Cu9irthDnkYvpEteLZ",
				"imageDate": "2021-02-22T07:53:00.000Z"
			},
			{
				"fileName": "IDR661.T.202102220759.png",
				"origSource": "http://www.bom.gov.au/radar/IDR661.T.202102220759.png",
				"source": "https://lh3.googleusercontent.com/d/1s_WT6-nGPaiK1VoTZ7IqQrIKFxWvfB1z",
				"imageDate": "2021-02-22T07:59:00.000Z"
			},
			{
				"fileName": "IDR661.T.202102220805.png",
				"origSource": "http://www.bom.gov.au/radar/IDR661.T.202102220805.png",
				"source": "https://lh3.googleusercontent.com/d/1_9Phrz87OAu3VddmdRh2m46vzrd0ppC5",
				"imageDate": "2021-02-22T08:05:00.000Z"
			},
			{
				"fileName": "IDR661.T.202102220811.png",
				"origSource": "http://www.bom.gov.au/radar/IDR661.T.202102220811.png",
				"source": "https://lh3.googleusercontent.com/d/1Oi3nhCntKbrFCmiwELxXKBpRYgfA54uZ",
				"imageDate": "2021-02-22T08:11:00.000Z"
			},
			{
				"fileName": "IDR661.T.202102220817.png",
				"origSource": "http://www.bom.gov.au/radar/IDR661.T.202102220817.png",
				"source": "https://lh3.googleusercontent.com/d/1lEGD2_H2lX4p0SgdnZpchRDbvalB-tBG",
				"imageDate": "2021-02-22T08:17:00.000Z"
			}
		],
		"error": null
	},
	"IDR662": {
		"name": "IDR662",
		"range": 256,
		"bounds": [
			[
				150.70305,
				-25.3863
			],
			[
				155.79741,
				-25.38595
			],
			[
				155.90765,
				-29.98708
			],
			[
				150.59369,
				-29.9875
			]
		],
		"title": "256 km Brisbane (Mt Stapylton)",
		"images": [
			{
				"fileName": "IDR662.T.202102220742.png",
				"origSource": "http://www.bom.gov.au/radar/IDR662.T.202102220742.png",
				"source": "https://lh3.googleusercontent.com/d/1sD-_tuI_0skvLUcSyN7iN1YV-fFnzPcd",
				"imageDate": "2021-02-22T07:42:00.000Z"
			},
			{
				"fileName": "IDR662.T.202102220742.png",
				"origSource": "http://www.bom.gov.au/radar/IDR662.T.202102220742.png",
				"source": "https://lh3.googleusercontent.com/d/1sD-_tuI_0skvLUcSyN7iN1YV-fFnzPcd",
				"imageDate": "2021-02-22T07:42:00.000Z"
			},
			{
				"fileName": "IDR662.T.202102220748.png",
				"origSource": "http://www.bom.gov.au/radar/IDR662.T.202102220748.png",
				"source": "https://lh3.googleusercontent.com/d/1WV487M3J4nTXMvq_-NBSwe-5bSeDAr5R",
				"imageDate": "2021-02-22T07:48:00.000Z"
			},
			{
				"fileName": "IDR662.T.202102220754.png",
				"origSource": "http://www.bom.gov.au/radar/IDR662.T.202102220754.png",
				"source": "https://lh3.googleusercontent.com/d/1tUySttxSzqya6621vQzlIzTr01z2uiKR",
				"imageDate": "2021-02-22T07:54:00.000Z"
			},
			{
				"fileName": "IDR662.T.202102220800.png",
				"origSource": "http://www.bom.gov.au/radar/IDR662.T.202102220800.png",
				"source": "https://lh3.googleusercontent.com/d/15Oy5rpAoHMyfXWVBEQ-buEuM47EuhnbB",
				"imageDate": "2021-02-22T08:00:00.000Z"
			},
			{
				"fileName": "IDR662.T.202102220806.png",
				"origSource": "http://www.bom.gov.au/radar/IDR662.T.202102220806.png",
				"source": "https://lh3.googleusercontent.com/d/1gJZdXqCEis_iIpAhRnzRVHFgpQkW2wNJ",
				"imageDate": "2021-02-22T08:06:00.000Z"
			},
			{
				"fileName": "IDR662.T.202102220812.png",
				"origSource": "http://www.bom.gov.au/radar/IDR662.T.202102220812.png",
				"source": "https://lh3.googleusercontent.com/d/1MbbBsQA3uHUVO0xuZic6PFzdHMnw03vV",
				"imageDate": "2021-02-22T08:12:00.000Z"
			}
		],
		"error": null
	},
	"IDR663": {
		"name": "IDR663",
		"range": 128,
		"bounds": [
			[
				151.95828,
				-26.5564
			],
			[
				154.53113,
				-26.55632
			],
			[
				154.55867,
				-28.85755
			],
			[
				151.93095,
				-28.85765
			]
		],
		"title": "128 km Brisbane (Mt Stapylton)",
		"images": [
			{
				"fileName": "IDR663.T.202102220742.png",
				"origSource": "http://www.bom.gov.au/radar/IDR663.T.202102220742.png",
				"source": "https://lh3.googleusercontent.com/d/1jB5xRzxdAkZDzaceZTNdoE1GpJLBvXmi",
				"imageDate": "2021-02-22T07:42:00.000Z"
			},
			{
				"fileName": "IDR663.T.202102220742.png",
				"origSource": "http://www.bom.gov.au/radar/IDR663.T.202102220742.png",
				"source": "https://lh3.googleusercontent.com/d/1jB5xRzxdAkZDzaceZTNdoE1GpJLBvXmi",
				"imageDate": "2021-02-22T07:42:00.000Z"
			},
			{
				"fileName": "IDR663.T.202102220748.png",
				"origSource": "http://www.bom.gov.au/radar/IDR663.T.202102220748.png",
				"source": "https://lh3.googleusercontent.com/d/1LBKPkcfUNzhzW8Mtl2gbu-ffFCx0ZM5o",
				"imageDate": "2021-02-22T07:48:00.000Z"
			},
			{
				"fileName": "IDR663.T.202102220754.png",
				"origSource": "http://www.bom.gov.au/radar/IDR663.T.202102220754.png",
				"source": "https://lh3.googleusercontent.com/d/1bC14AK4YspR7IwPUZZo4ytB7ejuf2Xi4",
				"imageDate": "2021-02-22T07:54:00.000Z"
			},
			{
				"fileName": "IDR663.T.202102220800.png",
				"origSource": "http://www.bom.gov.au/radar/IDR663.T.202102220800.png",
				"source": "https://lh3.googleusercontent.com/d/1LrGAp1umNO_mx6qIKopiWYUGi0v7fM4A",
				"imageDate": "2021-02-22T08:00:00.000Z"
			},
			{
				"fileName": "IDR663.T.202102220806.png",
				"origSource": "http://www.bom.gov.au/radar/IDR663.T.202102220806.png",
				"source": "https://lh3.googleusercontent.com/d/1lN8TAVaptmjkNhyavj8q6XO0xAIuac9u",
				"imageDate": "2021-02-22T08:06:00.000Z"
			},
			{
				"fileName": "IDR663.T.202102220812.png",
				"origSource": "http://www.bom.gov.au/radar/IDR663.T.202102220812.png",
				"source": "https://lh3.googleusercontent.com/d/1ymwsG-dbfvu1C0OhR8q5GA58jx7LoCV2",
				"imageDate": "2021-02-22T08:12:00.000Z"
			}
		],
		"error": null
	},
	"IDR664": {
		"name": "IDR664",
		"range": 64,
		"bounds": [
			[
				152.59523,
				-27.13828
			],
			[
				153.88959,
				-27.13826
			],
			[
				153.89648,
				-28.2901
			],
			[
				152.58838,
				-28.29012
			]
		],
		"title": "64 km Brisbane (Mt Stapylton)",
		"images": [
			{
				"fileName": "IDR664.T.202102220742.png",
				"origSource": "http://www.bom.gov.au/radar/IDR664.T.202102220742.png",
				"source": "https://lh3.googleusercontent.com/d/1EQxbsCZj5Qtf_tMZcNvO-OwjnfxJTAjD",
				"imageDate": "2021-02-22T07:42:00.000Z"
			},
			{
				"fileName": "IDR664.T.202102220742.png",
				"origSource": "http://www.bom.gov.au/radar/IDR664.T.202102220742.png",
				"source": "https://lh3.googleusercontent.com/d/1EQxbsCZj5Qtf_tMZcNvO-OwjnfxJTAjD",
				"imageDate": "2021-02-22T07:42:00.000Z"
			},
			{
				"fileName": "IDR664.T.202102220748.png",
				"origSource": "http://www.bom.gov.au/radar/IDR664.T.202102220748.png",
				"source": "https://lh3.googleusercontent.com/d/1pO26aSJ5Z2YXJBxwJPuTMGOc8V_hm6Ae",
				"imageDate": "2021-02-22T07:48:00.000Z"
			},
			{
				"fileName": "IDR664.T.202102220754.png",
				"origSource": "http://www.bom.gov.au/radar/IDR664.T.202102220754.png",
				"source": "https://lh3.googleusercontent.com/d/19sW4MmjH31Al8MQh_8phIk_tA-HiVMW0",
				"imageDate": "2021-02-22T07:54:00.000Z"
			},
			{
				"fileName": "IDR664.T.202102220800.png",
				"origSource": "http://www.bom.gov.au/radar/IDR664.T.202102220800.png",
				"source": "https://lh3.googleusercontent.com/d/1dYtK8q0noK3XmARoYBpkpNlXcWY3HHTV",
				"imageDate": "2021-02-22T08:00:00.000Z"
			},
			{
				"fileName": "IDR664.T.202102220806.png",
				"origSource": "http://www.bom.gov.au/radar/IDR664.T.202102220806.png",
				"source": "https://lh3.googleusercontent.com/d/1HURr-uKcuaaq-kBkiGvqP6-HSWUWLllE",
				"imageDate": "2021-02-22T08:06:00.000Z"
			},
			{
				"fileName": "IDR664.T.202102220812.png",
				"origSource": "http://www.bom.gov.au/radar/IDR664.T.202102220812.png",
				"source": "https://lh3.googleusercontent.com/d/1uhTym3us21cpKW8Q4YHILAdwWpoEWgg4",
				"imageDate": "2021-02-22T08:12:00.000Z"
			}
		],
		"error": null
	},
	"IDR671": {
		"name": "IDR671",
		"range": 512,
		"bounds": [
			[
				142.42256,
				-21.73685
			],
			[
				152.30754,
				-21.7359
			],
			[
				152.71892,
				-30.90922
			],
			[
				142.01378,
				-30.91064
			]
		],
		"title": "512 km composite Warrego",
		"images": [
			{
				"fileName": "IDR671.T.202102220751.png",
				"origSource": "http://www.bom.gov.au/radar/IDR671.T.202102220751.png",
				"source": "https://lh3.googleusercontent.com/d/1aBc0q25g-utbACtUo0K7RdxvDVOUwY6a",
				"imageDate": "2021-02-22T07:51:00.000Z"
			},
			{
				"fileName": "IDR671.T.202102220756.png",
				"origSource": "http://www.bom.gov.au/radar/IDR671.T.202102220756.png",
				"source": "https://lh3.googleusercontent.com/d/1xfG5DsIuB3HpLoO8Y8DFK6M3-wANG737",
				"imageDate": "2021-02-22T07:56:00.000Z"
			},
			{
				"fileName": "IDR671.T.202102220801.png",
				"origSource": "http://www.bom.gov.au/radar/IDR671.T.202102220801.png",
				"source": "https://lh3.googleusercontent.com/d/1SksbnTmQ65SebU1TJ3rP6GOcnhn4T0jO",
				"imageDate": "2021-02-22T08:01:00.000Z"
			},
			{
				"fileName": "IDR671.T.202102220806.png",
				"origSource": "http://www.bom.gov.au/radar/IDR671.T.202102220806.png",
				"source": "https://lh3.googleusercontent.com/d/12egEiHI-MpVSPgvGvP5veE7Xyt4BMm1F",
				"imageDate": "2021-02-22T08:06:00.000Z"
			},
			{
				"fileName": "IDR671.T.202102220811.png",
				"origSource": "http://www.bom.gov.au/radar/IDR671.T.202102220811.png",
				"source": "https://lh3.googleusercontent.com/d/17BjqqLo2ID8-FMukoWy8KRZDxIO_9l8t",
				"imageDate": "2021-02-22T08:11:00.000Z"
			},
			{
				"fileName": "IDR671.T.202102220816.png",
				"origSource": "http://www.bom.gov.au/radar/IDR671.T.202102220816.png",
				"source": "https://lh3.googleusercontent.com/d/1xkspPSnHDLP1gs4CgIGkhUwxvocPdMtJ",
				"imageDate": "2021-02-22T08:16:00.000Z"
			},
			{
				"fileName": "IDR671.T.202102220821.png",
				"origSource": "http://www.bom.gov.au/radar/IDR671.T.202102220821.png",
				"source": "https://lh3.googleusercontent.com/d/1cE3rWvjBdaw1NKuFI0v8oI2CIRUFAhMx",
				"imageDate": "2021-02-22T08:21:00.000Z"
			}
		],
		"error": null
	},
	"IDR672": {
		"name": "IDR672",
		"range": 256,
		"bounds": [
			[
				144.83536,
				-24.10475
			],
			[
				149.88277,
				-24.10443
			],
			[
				149.98613,
				-28.71053
			],
			[
				144.7328,
				-28.71093
			]
		],
		"title": "256 km Warrego",
		"images": [
			{
				"fileName": "IDR672.T.202102220745.png",
				"origSource": "http://www.bom.gov.au/radar/IDR672.T.202102220745.png",
				"source": "https://lh3.googleusercontent.com/d/1BN__bFUs467UFpc8BtGQVtjf4becRWvi",
				"imageDate": "2021-02-22T07:45:00.000Z"
			},
			{
				"fileName": "IDR672.T.202102220750.png",
				"origSource": "http://www.bom.gov.au/radar/IDR672.T.202102220750.png",
				"source": "https://lh3.googleusercontent.com/d/1AVjMVBQ3Xsb0oxkjRNcPoKumeshOjFpY",
				"imageDate": "2021-02-22T07:50:00.000Z"
			},
			{
				"fileName": "IDR672.T.202102220755.png",
				"origSource": "http://www.bom.gov.au/radar/IDR672.T.202102220755.png",
				"source": "https://lh3.googleusercontent.com/d/1M9V_iacnXaNSu_uhh9JKNrywvvMO2y5A",
				"imageDate": "2021-02-22T07:55:00.000Z"
			},
			{
				"fileName": "IDR672.T.202102220800.png",
				"origSource": "http://www.bom.gov.au/radar/IDR672.T.202102220800.png",
				"source": "https://lh3.googleusercontent.com/d/144G_w-NtaoLn2DHsoj-n_Htx0jrH4AID",
				"imageDate": "2021-02-22T08:00:00.000Z"
			},
			{
				"fileName": "IDR672.T.202102220805.png",
				"origSource": "http://www.bom.gov.au/radar/IDR672.T.202102220805.png",
				"source": "https://lh3.googleusercontent.com/d/1CdZGeskMn00hWu1xb19Lcfo8GXDBsLt9",
				"imageDate": "2021-02-22T08:05:00.000Z"
			},
			{
				"fileName": "IDR672.T.202102220810.png",
				"origSource": "http://www.bom.gov.au/radar/IDR672.T.202102220810.png",
				"source": "https://lh3.googleusercontent.com/d/1m3o9XvNwEnUC8p_vsYZT0jN4mRC6oTbv",
				"imageDate": "2021-02-22T08:10:00.000Z"
			},
			{
				"fileName": "IDR672.T.202102220815.png",
				"origSource": "http://www.bom.gov.au/radar/IDR672.T.202102220815.png",
				"source": "https://lh3.googleusercontent.com/d/19N-Uz-gVYch3gPwYVgVa6aRCRIMdPIPK",
				"imageDate": "2021-02-22T08:15:00.000Z"
			}
		],
		"error": null
	},
	"IDR673": {
		"name": "IDR673",
		"range": 128,
		"bounds": [
			[
				146.08232,
				-25.28016
			],
			[
				148.62711,
				-25.28007
			],
			[
				148.65288,
				-27.58098
			],
			[
				146.05678,
				-27.58109
			]
		],
		"title": "128 km Warrego",
		"images": [
			{
				"fileName": "IDR673.T.202102220745.png",
				"origSource": "http://www.bom.gov.au/radar/IDR673.T.202102220745.png",
				"source": "https://lh3.googleusercontent.com/d/1kAULiA_yly8OBULtP3aIThKwppvhrDxf",
				"imageDate": "2021-02-22T07:45:00.000Z"
			},
			{
				"fileName": "IDR673.T.202102220750.png",
				"origSource": "http://www.bom.gov.au/radar/IDR673.T.202102220750.png",
				"source": "https://lh3.googleusercontent.com/d/1gksh0w9RKUL1dYj6UgOI-ODFL921WyqY",
				"imageDate": "2021-02-22T07:50:00.000Z"
			},
			{
				"fileName": "IDR673.T.202102220755.png",
				"origSource": "http://www.bom.gov.au/radar/IDR673.T.202102220755.png",
				"source": "https://lh3.googleusercontent.com/d/1u4afyV-8JSW_6xN3BGgg1p91LHDiIyGb",
				"imageDate": "2021-02-22T07:55:00.000Z"
			},
			{
				"fileName": "IDR673.T.202102220800.png",
				"origSource": "http://www.bom.gov.au/radar/IDR673.T.202102220800.png",
				"source": "https://lh3.googleusercontent.com/d/1Om-e4xlVsnL4FFvnThK_Iv9URb5SpHnV",
				"imageDate": "2021-02-22T08:00:00.000Z"
			},
			{
				"fileName": "IDR673.T.202102220805.png",
				"origSource": "http://www.bom.gov.au/radar/IDR673.T.202102220805.png",
				"source": "https://lh3.googleusercontent.com/d/1jvNd0skuo9WkCSZKYrcBjl9nFovVFF3z",
				"imageDate": "2021-02-22T08:05:00.000Z"
			},
			{
				"fileName": "IDR673.T.202102220810.png",
				"origSource": "http://www.bom.gov.au/radar/IDR673.T.202102220810.png",
				"source": "https://lh3.googleusercontent.com/d/1U0gjLiQaPf2ueOQLNbX8e_y6vXbG_LVl",
				"imageDate": "2021-02-22T08:10:00.000Z"
			},
			{
				"fileName": "IDR673.T.202102220815.png",
				"origSource": "http://www.bom.gov.au/radar/IDR673.T.202102220815.png",
				"source": "https://lh3.googleusercontent.com/d/1_kJXljQZVYNhwm6E5VU1zeBlvvjjy-IC",
				"imageDate": "2021-02-22T08:15:00.000Z"
			}
		],
		"error": null
	}
}